{
    "version": "0.4",
    "title": "Blog",
    "type": "page",
    "metadata": {
        "template_type": "single-page",
        "include_in_zip": "1",
        "elementor_pro_required": "1",
        "wp_page_template": "elementor_header_footer"
    },
    "content": [
        {
            "id": "2b9ba981",
            "settings": {
                "gap": "no",
                "overflow": "hidden",
                "structure": "20",
                "background_background": "classic",
                "background_image": {
                    "url": "https:\/\/templatekits.themewarrior.com\/autodrive\/wp-content\/uploads\/sites\/42\/2022\/01\/hero-blog.jpg",
                    "id": "518",
                    "alt": "",
                    "source": "library"
                },
                "background_position": "center center",
                "background_repeat": "no-repeat",
                "background_size": "cover",
                "background_overlay_background": "classic",
                "background_overlay_opacity": {
                    "unit": "px",
                    "size": "0.6",
                    "sizes": []
                },
                "padding": {
                    "unit": "px",
                    "top": "220",
                    "right": "0",
                    "bottom": "180",
                    "left": "0",
                    "isLinked": ""
                },
                "padding_tablet": {
                    "unit": "px",
                    "top": "150",
                    "right": "32",
                    "bottom": "100",
                    "left": "32",
                    "isLinked": ""
                },
                "padding_mobile": {
                    "unit": "px",
                    "top": "120",
                    "right": "16",
                    "bottom": "50",
                    "left": "16",
                    "isLinked": ""
                },
                "__globals__": {
                    "background_overlay_color": "globals\/colors?id=text"
                },
                "_title": "Section: Hero Page"
            },
            "elements": [
                {
                    "id": "1798b8d3",
                    "settings": {
                        "_column_size": "50",
                        "space_between_widgets": "16"
                    },
                    "elements": [
                        {
                            "id": "667e720e",
                            "settings": {
                                "title": "Updates",
                                "header_size": "h5",
                                "__globals__": {
                                    "title_color": "globals\/colors?id=accent",
                                    "typography_typography": "globals\/typography?id=7da4305"
                                },
                                "_animation": "fadeInDown"
                            },
                            "elements": [],
                            "isInner": false,
                            "widgetType": "heading",
                            "elType": "widget"
                        },
                        {
                            "id": "347c8de4",
                            "settings": {
                                "title": "Page Title",
                                "header_size": "h1",
                                "_margin": {
                                    "unit": "px",
                                    "top": "-8",
                                    "right": "0",
                                    "bottom": "0",
                                    "left": "0",
                                    "isLinked": ""
                                },
                                "__globals__": {
                                    "title_color": "globals\/colors?id=3e5f3fc",
                                    "typography_typography": "globals\/typography?id=0046bd7"
                                },
                                "_animation": "fadeInUp",
                                "__dynamic__": {
                                    "title": "[elementor-tag id=\"3d6d8af\" name=\"page-title\" settings=\"%7B%7D\"]"
                                }
                            },
                            "elements": [],
                            "isInner": false,
                            "widgetType": "heading",
                            "elType": "widget"
                        }
                    ],
                    "isInner": "",
                    "elType": "column"
                },
                {
                    "id": "77f87bb7",
                    "settings": {
                        "_column_size": "50",
                        "content_position": "bottom",
                        "align": "flex-end",
                        "align_mobile": "flex-start",
                        "margin_mobile": {
                            "unit": "px",
                            "top": "16",
                            "right": "0",
                            "bottom": "0",
                            "left": "0",
                            "isLinked": ""
                        },
                        "padding": {
                            "unit": "px",
                            "top": "0",
                            "right": "0",
                            "bottom": "14",
                            "left": "0",
                            "isLinked": ""
                        },
                        "padding_tablet": {
                            "unit": "px",
                            "top": "0",
                            "right": "0",
                            "bottom": "12",
                            "left": "0",
                            "isLinked": ""
                        }
                    },
                    "elements": [
                        {
                            "id": "358c48f2",
                            "settings": {
                                "view": "inline",
                                "icon_list": [
                                    {
                                        "text": "home",
                                        "selected_icon": {
                                            "value": "fas fa-home",
                                            "library": "fa-solid"
                                        },
                                        "_id": "8d78c5c"
                                    },
                                    {
                                        "text": "Page Title",
                                        "selected_icon": {
                                            "value": "fas fa-angle-right",
                                            "library": "fa-solid"
                                        },
                                        "_id": "ca5609a",
                                        "__dynamic__": {
                                            "text": "[elementor-tag id=\"3fbaa1a\" name=\"page-title\" settings=\"%7B%7D\"]"
                                        }
                                    }
                                ],
                                "icon_align": "right",
                                "icon_size": {
                                    "unit": "px",
                                    "size": "15",
                                    "sizes": []
                                },
                                "text_indent": {
                                    "unit": "px",
                                    "size": "16",
                                    "sizes": []
                                },
                                "_padding": {
                                    "unit": "px",
                                    "top": "16",
                                    "right": "16",
                                    "bottom": "16",
                                    "left": "16",
                                    "isLinked": "1"
                                },
                                "_padding_mobile": {
                                    "unit": "px",
                                    "top": "12",
                                    "right": "12",
                                    "bottom": "12",
                                    "left": "12",
                                    "isLinked": "1"
                                },
                                "_animation": "fadeInRight",
                                "_background_background": "classic",
                                "_element_width": "auto",
                                "_element_vertical_align": "center",
                                "__globals__": {
                                    "_background_color": "globals\/colors?id=secondary",
                                    "icon_color": "globals\/colors?id=3e5f3fc",
                                    "icon_color_hover": "globals\/colors?id=3e5f3fc",
                                    "text_color": "globals\/colors?id=3e5f3fc",
                                    "text_color_hover": "globals\/colors?id=3e5f3fc",
                                    "icon_typography_typography": "globals\/typography?id=cfff929"
                                }
                            },
                            "elements": [],
                            "isInner": false,
                            "widgetType": "icon-list",
                            "elType": "widget"
                        }
                    ],
                    "isInner": "",
                    "elType": "column"
                }
            ],
            "isInner": "",
            "elType": "section"
        },
        {
            "id": "179c36be",
            "settings": {
                "gap": "no",
                "__globals__": {
                    "background_color": "globals\/colors?id=e5c2ee6"
                },
                "_title": "Section: latest post",
                "margin": {
                    "unit": "px",
                    "top": "0",
                    "right": "0",
                    "bottom": "0",
                    "left": "0",
                    "isLinked": ""
                },
                "margin_tablet": {
                    "unit": "px",
                    "top": "0",
                    "right": "0",
                    "bottom": "0",
                    "left": "0",
                    "isLinked": ""
                },
                "padding": {
                    "unit": "px",
                    "top": "100",
                    "right": "0",
                    "bottom": "100",
                    "left": "0",
                    "isLinked": ""
                },
                "padding_tablet": {
                    "unit": "px",
                    "top": "50",
                    "right": "32",
                    "bottom": "50",
                    "left": "32",
                    "isLinked": ""
                },
                "padding_mobile": {
                    "unit": "px",
                    "top": "32",
                    "right": "16",
                    "bottom": "32",
                    "left": "16",
                    "isLinked": ""
                }
            },
            "elements": [
                {
                    "id": "18d104d8",
                    "settings": {
                        "_column_size": "100"
                    },
                    "elements": [
                        {
                            "id": "5ec38dde",
                            "settings": {
                                "content_width": {
                                    "unit": "px",
                                    "size": "610",
                                    "sizes": []
                                },
                                "gap": "no",
                                "margin": {
                                    "unit": "px",
                                    "top": "0",
                                    "right": "0",
                                    "bottom": "64",
                                    "left": "0",
                                    "isLinked": ""
                                },
                                "margin_tablet": {
                                    "unit": "px",
                                    "top": "0",
                                    "right": "0",
                                    "bottom": "32",
                                    "left": "0",
                                    "isLinked": ""
                                },
                                "margin_mobile": {
                                    "unit": "px",
                                    "top": "",
                                    "right": "0",
                                    "bottom": "",
                                    "left": "0",
                                    "isLinked": "1"
                                }
                            },
                            "elements": [
                                {
                                    "id": "63f6bd38",
                                    "settings": {
                                        "_column_size": "100",
                                        "space_between_widgets": "16"
                                    },
                                    "elements": [
                                        {
                                            "id": "7b89fad9",
                                            "settings": {
                                                "title": "updates",
                                                "header_size": "h5",
                                                "align": "center",
                                                "__globals__": {
                                                    "title_color": "globals\/colors?id=primary",
                                                    "typography_typography": "globals\/typography?id=7da4305"
                                                }
                                            },
                                            "elements": [],
                                            "isInner": false,
                                            "widgetType": "heading",
                                            "elType": "widget"
                                        },
                                        {
                                            "id": "57351248",
                                            "settings": {
                                                "title": "Latest news",
                                                "align": "center",
                                                "_margin": {
                                                    "unit": "px",
                                                    "top": "-8",
                                                    "right": "0",
                                                    "bottom": "0",
                                                    "left": "0",
                                                    "isLinked": ""
                                                },
                                                "__globals__": {
                                                    "title_color": "globals\/colors?id=text",
                                                    "typography_typography": "globals\/typography?id=1ff2e5b"
                                                },
                                                "_animation": "fadeInUp"
                                            },
                                            "elements": [],
                                            "isInner": false,
                                            "widgetType": "heading",
                                            "elType": "widget"
                                        },
                                        {
                                            "id": "15d5e2c3",
                                            "settings": {
                                                "title": "Odio eu viverra tincidunt tristique ullamcorper blandit dipiscing nunc risus integer at elementum cursus. Lorem justo a felis elit amet.",
                                                "header_size": "div",
                                                "align": "center",
                                                "__globals__": {
                                                    "title_color": "globals\/colors?id=25db21a",
                                                    "typography_typography": "globals\/typography?id=text"
                                                },
                                                "_padding": {
                                                    "unit": "px",
                                                    "top": "0",
                                                    "right": "0",
                                                    "bottom": "0",
                                                    "left": "0",
                                                    "isLinked": "1"
                                                }
                                            },
                                            "elements": [],
                                            "isInner": false,
                                            "widgetType": "heading",
                                            "elType": "widget"
                                        }
                                    ],
                                    "isInner": "1",
                                    "elType": "column"
                                }
                            ],
                            "isInner": "1",
                            "elType": "section"
                        },
                        {
                            "id": "66cdcf5d",
                            "settings": {
                                "classic_posts_per_page": "2",
                                "classic_thumbnail_size_size": "medium_large",
                                "classic_meta_separator": "",
                                "classic_read_more_text": "Read More \u00bb",
                                "cards_meta_separator": "\u2022",
                                "cards_read_more_text": "Read More \u00bb",
                                "full_content_meta_separator": "\/\/\/",
                                "pagination_page_limit": "5",
                                "pagination_prev_label": "&laquo; Previous",
                                "pagination_next_label": "Next &raquo;",
                                "text": "Load More",
                                "load_more_no_posts_custom_message": "No more posts to show",
                                "classic_item_ratio": {
                                    "unit": "px",
                                    "size": "0.5",
                                    "sizes": []
                                },
                                "classic_title_tag": "h4",
                                "classic_show_excerpt": "",
                                "classic_row_gap": {
                                    "unit": "px",
                                    "size": "30",
                                    "sizes": []
                                },
                                "classic_content_padding": {
                                    "unit": "px",
                                    "top": "32",
                                    "right": "32",
                                    "bottom": "32",
                                    "left": "32",
                                    "isLinked": "1"
                                },
                                "classic_box_shadow_box_shadow": {
                                    "horizontal": "0",
                                    "vertical": "10",
                                    "blur": "20",
                                    "spread": "0",
                                    "color": "rgba(10.000000000000007, 25.000000000000043, 49.00000000000001, 0.05)"
                                },
                                "classic_image_spacing": {
                                    "unit": "px",
                                    "size": "0",
                                    "sizes": []
                                },
                                "classic_title_spacing": {
                                    "unit": "px",
                                    "size": "8",
                                    "sizes": []
                                },
                                "classic_meta_spacing": {
                                    "unit": "px",
                                    "size": "8",
                                    "sizes": []
                                },
                                "classic_read_more_spacing": {
                                    "unit": "px",
                                    "size": "0",
                                    "sizes": []
                                },
                                "_animation": "fadeInUp",
                                "__globals__": {
                                    "classic_title_color": "globals\/colors?id=3e5f3fc",
                                    "classic_title_typography_typography": "globals\/typography?id=b45b6c7",
                                    "classic_meta_color": "globals\/colors?id=3e5f3fc",
                                    "classic_meta_separator_color": "globals\/colors?id=3e5f3fc",
                                    "classic_meta_typography_typography": "globals\/typography?id=text",
                                    "classic_read_more_color": "globals\/colors?id=accent",
                                    "classic_read_more_typography_typography": "globals\/typography?id=eab332b",
                                    "classic_box_bg_color": "globals\/colors?id=text"
                                },
                                "classic_columns": "2",
                                "posts_order": "asc"
                            },
                            "elements": [],
                            "isInner": false,
                            "widgetType": "posts",
                            "elType": "widget"
                        }
                    ],
                    "isInner": "",
                    "elType": "column"
                }
            ],
            "isInner": "",
            "elType": "section"
        },
        {
            "id": "3af92541",
            "settings": {
                "gap": "no",
                "padding": {
                    "unit": "px",
                    "top": "0",
                    "right": "0",
                    "bottom": "100",
                    "left": "0",
                    "isLinked": ""
                },
                "_title": "Section: other article",
                "padding_tablet": {
                    "unit": "px",
                    "top": "0",
                    "right": "32",
                    "bottom": "50",
                    "left": "32",
                    "isLinked": ""
                },
                "padding_mobile": {
                    "unit": "px",
                    "top": "0",
                    "right": "16",
                    "bottom": "32",
                    "left": "16",
                    "isLinked": ""
                }
            },
            "elements": [
                {
                    "id": "6e3f134f",
                    "settings": {
                        "_column_size": "100"
                    },
                    "elements": [
                        {
                            "id": "95e5969",
                            "settings": {
                                "content_width": {
                                    "unit": "px",
                                    "size": "610",
                                    "sizes": []
                                },
                                "gap": "no",
                                "margin": {
                                    "unit": "px",
                                    "top": "0",
                                    "right": "0",
                                    "bottom": "64",
                                    "left": "0",
                                    "isLinked": ""
                                },
                                "margin_tablet": {
                                    "unit": "px",
                                    "top": "0",
                                    "right": "0",
                                    "bottom": "32",
                                    "left": "0",
                                    "isLinked": ""
                                },
                                "margin_mobile": {
                                    "unit": "px",
                                    "top": "",
                                    "right": "0",
                                    "bottom": "",
                                    "left": "0",
                                    "isLinked": "1"
                                }
                            },
                            "elements": [
                                {
                                    "id": "153f674a",
                                    "settings": {
                                        "_column_size": "100",
                                        "space_between_widgets": "16"
                                    },
                                    "elements": [
                                        {
                                            "id": "28e02bc3",
                                            "settings": {
                                                "title": "Articles",
                                                "header_size": "h5",
                                                "align": "center",
                                                "__globals__": {
                                                    "title_color": "globals\/colors?id=primary",
                                                    "typography_typography": "globals\/typography?id=7da4305"
                                                }
                                            },
                                            "elements": [],
                                            "isInner": false,
                                            "widgetType": "heading",
                                            "elType": "widget"
                                        },
                                        {
                                            "id": "7f588453",
                                            "settings": {
                                                "title": "explore More",
                                                "align": "center",
                                                "_margin": {
                                                    "unit": "px",
                                                    "top": "-8",
                                                    "right": "0",
                                                    "bottom": "0",
                                                    "left": "0",
                                                    "isLinked": ""
                                                },
                                                "__globals__": {
                                                    "title_color": "globals\/colors?id=text",
                                                    "typography_typography": "globals\/typography?id=1ff2e5b"
                                                },
                                                "_animation": "fadeInUp"
                                            },
                                            "elements": [],
                                            "isInner": false,
                                            "widgetType": "heading",
                                            "elType": "widget"
                                        },
                                        {
                                            "id": "1fff2f9f",
                                            "settings": {
                                                "title": "Odio eu viverra tincidunt tristique ullamcorper blandit dipiscing nunc risus integer at elementum cursus. Lorem justo a felis elit amet.",
                                                "header_size": "div",
                                                "align": "center",
                                                "__globals__": {
                                                    "title_color": "globals\/colors?id=25db21a",
                                                    "typography_typography": "globals\/typography?id=text"
                                                },
                                                "_padding": {
                                                    "unit": "px",
                                                    "top": "0",
                                                    "right": "0",
                                                    "bottom": "0",
                                                    "left": "0",
                                                    "isLinked": "1"
                                                }
                                            },
                                            "elements": [],
                                            "isInner": false,
                                            "widgetType": "heading",
                                            "elType": "widget"
                                        }
                                    ],
                                    "isInner": "1",
                                    "elType": "column"
                                }
                            ],
                            "isInner": "1",
                            "elType": "section"
                        },
                        {
                            "id": "1e4c2af0",
                            "settings": {
                                "classic_posts_per_page": "9",
                                "classic_thumbnail_size_size": "medium_large",
                                "classic_meta_separator": "",
                                "classic_read_more_text": "Read More \u00bb",
                                "cards_meta_separator": "\u2022",
                                "cards_read_more_text": "Read More \u00bb",
                                "full_content_meta_separator": "\/\/\/",
                                "pagination_page_limit": "5",
                                "pagination_prev_label": "&laquo; Previous",
                                "pagination_next_label": "Next &raquo;",
                                "text": "Load More",
                                "load_more_no_posts_custom_message": "No more posts to show",
                                "classic_item_ratio": {
                                    "unit": "px",
                                    "size": "0.6",
                                    "sizes": []
                                },
                                "classic_title_tag": "h4",
                                "classic_show_excerpt": "",
                                "classic_row_gap": {
                                    "unit": "px",
                                    "size": "30",
                                    "sizes": []
                                },
                                "classic_content_padding": {
                                    "unit": "px",
                                    "top": "32",
                                    "right": "32",
                                    "bottom": "32",
                                    "left": "32",
                                    "isLinked": "1"
                                },
                                "classic_box_shadow_box_shadow_type": "yes",
                                "classic_box_shadow_box_shadow": {
                                    "horizontal": "0",
                                    "vertical": "10",
                                    "blur": "20",
                                    "spread": "0",
                                    "color": "rgba(10.000000000000007, 25.000000000000043, 49.00000000000001, 0.05)"
                                },
                                "classic_image_spacing": {
                                    "unit": "px",
                                    "size": "0",
                                    "sizes": []
                                },
                                "classic_title_spacing": {
                                    "unit": "px",
                                    "size": "8",
                                    "sizes": []
                                },
                                "classic_meta_spacing": {
                                    "unit": "px",
                                    "size": "8",
                                    "sizes": []
                                },
                                "classic_read_more_spacing": {
                                    "unit": "px",
                                    "size": "0",
                                    "sizes": []
                                },
                                "_animation": "fadeInUp",
                                "__globals__": {
                                    "classic_title_color": "globals\/colors?id=text",
                                    "classic_title_typography_typography": "globals\/typography?id=b45b6c7",
                                    "classic_meta_color": "globals\/colors?id=25db21a",
                                    "classic_meta_separator_color": "globals\/colors?id=25db21a",
                                    "classic_meta_typography_typography": "globals\/typography?id=text",
                                    "classic_read_more_color": "globals\/colors?id=primary",
                                    "classic_read_more_typography_typography": "globals\/typography?id=eab332b"
                                },
                                "posts_orderby": "rand"
                            },
                            "elements": [],
                            "isInner": false,
                            "widgetType": "posts",
                            "elType": "widget"
                        }
                    ],
                    "isInner": "",
                    "elType": "column"
                }
            ],
            "isInner": "",
            "elType": "section"
        }
    ]
}