{
    "version": "0.4",
    "title": "Coming soon",
    "type": "page",
    "metadata": {
        "template_type": "single-page",
        "include_in_zip": "1",
        "elementor_pro_required": "1",
        "wp_page_template": "elementor_canvas"
    },
    "content": [
        {
            "id": "26252d04",
            "settings": {
                "gap": "no",
                "height": "full",
                "background_background": "classic",
                "background_image": {
                    "url": "https:\/\/templatekits.themewarrior.com\/autodrive\/wp-content\/uploads\/sites\/42\/2022\/01\/comingsoon-bg-autodrive.jpg",
                    "id": "589",
                    "alt": "",
                    "source": "library"
                },
                "background_position": "center center",
                "background_repeat": "no-repeat",
                "background_size": "cover",
                "background_overlay_background": "classic",
                "background_overlay_opacity": {
                    "unit": "px",
                    "size": "0.6",
                    "sizes": []
                },
                "padding_mobile": {
                    "unit": "%",
                    "top": "25",
                    "right": "0",
                    "bottom": "50",
                    "left": "0",
                    "isLinked": ""
                },
                "__globals__": {
                    "background_overlay_color": "globals\/colors?id=text"
                },
                "_title": "Section: Coming soon",
                "structure": "20",
                "padding_tablet": {
                    "unit": "px",
                    "top": "0",
                    "right": "32",
                    "bottom": "0",
                    "left": "32",
                    "isLinked": ""
                }
            },
            "elements": [
                {
                    "id": "37a71e0b",
                    "settings": {
                        "_column_size": "50",
                        "_inline_size": "55",
                        "space_between_widgets": "16",
                        "padding_mobile": {
                            "unit": "px",
                            "top": "0",
                            "right": "16",
                            "bottom": "0",
                            "left": "16",
                            "isLinked": ""
                        },
                        "_inline_size_tablet": "75",
                        "content_position_mobile": "center"
                    },
                    "elements": [
                        {
                            "id": "325fcbe4",
                            "settings": {
                                "__dynamic__": {
                                    "image": "[elementor-tag id=\"\" name=\"site-logo\" settings=\"%7B%7D\"]",
                                    "link": "[elementor-tag id=\"\" name=\"site-url\" settings=\"%7B%7D\"]"
                                },
                                "align": "left",
                                "align_mobile": "center",
                                "link_to": "none",
                                "space_mobile": {
                                    "unit": "px",
                                    "size": "135",
                                    "sizes": []
                                },
                                "_padding": {
                                    "unit": "px",
                                    "top": "0",
                                    "right": "0",
                                    "bottom": "60",
                                    "left": "0",
                                    "isLinked": ""
                                },
                                "_padding_mobile": {
                                    "unit": "px",
                                    "top": "0",
                                    "right": "0",
                                    "bottom": "30",
                                    "left": "0",
                                    "isLinked": ""
                                }
                            },
                            "elements": [],
                            "isInner": false,
                            "widgetType": "theme-site-logo",
                            "elType": "widget"
                        },
                        {
                            "id": "55c2459d",
                            "settings": {
                                "title": "Coming soon",
                                "header_size": "h5",
                                "__globals__": {
                                    "title_color": "globals\/colors?id=accent",
                                    "typography_typography": "globals\/typography?id=7da4305"
                                },
                                "align_mobile": "center",
                                "align": "left"
                            },
                            "elements": [],
                            "isInner": false,
                            "widgetType": "heading",
                            "elType": "widget"
                        },
                        {
                            "id": "3869c069",
                            "settings": {
                                "title": "New Site Is Coming",
                                "header_size": "h1",
                                "_margin": {
                                    "unit": "px",
                                    "top": "-8",
                                    "right": "0",
                                    "bottom": "0",
                                    "left": "0",
                                    "isLinked": ""
                                },
                                "__globals__": {
                                    "title_color": "globals\/colors?id=3e5f3fc",
                                    "typography_typography": "globals\/typography?id=0046bd7"
                                },
                                "_animation": "fadeInUp",
                                "align": "left",
                                "align_mobile": "center"
                            },
                            "elements": [],
                            "isInner": false,
                            "widgetType": "heading",
                            "elType": "widget"
                        },
                        {
                            "id": "24e9a203",
                            "settings": {
                                "title": "Coming Soon, Please check again in the near future.",
                                "header_size": "div",
                                "align": "left",
                                "_animation": "fadeInDown",
                                "__globals__": {
                                    "typography_typography": "globals\/typography?id=text",
                                    "title_color": "globals\/colors?id=3e5f3fc"
                                },
                                "align_mobile": "center"
                            },
                            "elements": [],
                            "isInner": false,
                            "widgetType": "heading",
                            "elType": "widget"
                        },
                        {
                            "id": "f0e8094",
                            "settings": {
                                "gap": "no",
                                "margin": {
                                    "unit": "px",
                                    "top": "48",
                                    "right": "0",
                                    "bottom": "0",
                                    "left": "0",
                                    "isLinked": ""
                                }
                            },
                            "elements": [
                                {
                                    "id": "4abaf1b1",
                                    "settings": {
                                        "_column_size": "100",
                                        "space_between_widgets": "16"
                                    },
                                    "elements": [
                                        {
                                            "id": "3137b7cf",
                                            "settings": {
                                                "title": "We are launching in:",
                                                "header_size": "h4",
                                                "__globals__": {
                                                    "title_color": "globals\/colors?id=3e5f3fc",
                                                    "typography_typography": "globals\/typography?id=b45b6c7"
                                                },
                                                "align_mobile": "center",
                                                "align": "left"
                                            },
                                            "elements": [],
                                            "isInner": false,
                                            "widgetType": "heading",
                                            "elType": "widget"
                                        },
                                        {
                                            "id": "2b44b4ce",
                                            "settings": {
                                                "label_days": "Days",
                                                "label_hours": "Hours",
                                                "label_minutes": "Minutes",
                                                "label_seconds": "Seconds",
                                                "box_spacing": {
                                                    "unit": "px",
                                                    "size": "30",
                                                    "sizes": []
                                                },
                                                "box_spacing_tablet": {
                                                    "unit": "px",
                                                    "size": "20",
                                                    "sizes": []
                                                },
                                                "box_spacing_mobile": {
                                                    "unit": "px",
                                                    "size": "10",
                                                    "sizes": []
                                                },
                                                "_animation": "fadeInUp",
                                                "__globals__": {
                                                    "digits_color": "globals\/colors?id=text",
                                                    "digits_typography_typography": "globals\/typography?id=0046bd7",
                                                    "label_color": "globals\/colors?id=text",
                                                    "label_typography_typography": "globals\/typography?id=7da4305",
                                                    "box_background_color": "globals\/colors?id=accent"
                                                }
                                            },
                                            "elements": [],
                                            "isInner": false,
                                            "widgetType": "countdown",
                                            "elType": "widget"
                                        }
                                    ],
                                    "isInner": "1",
                                    "elType": "column"
                                }
                            ],
                            "isInner": "1",
                            "elType": "section"
                        }
                    ],
                    "isInner": "",
                    "elType": "column"
                },
                {
                    "id": "f2804fc",
                    "settings": {
                        "_column_size": "50",
                        "_inline_size": "45",
                        "_inline_size_tablet": "25"
                    },
                    "elements": [],
                    "isInner": "",
                    "elType": "column"
                }
            ],
            "isInner": "",
            "elType": "section"
        }
    ]
}